asyncio_zabbix_sender/__init__.py
asyncio_zabbix_sender/_measurements.py
asyncio_zabbix_sender/_protocol.py
asyncio_zabbix_sender/_response.py
asyncio_zabbix_sender/_util.py
asyncio_zabbix_sender/_zabbix_sender.py
asyncio_zabbix_sender/py.typed
asyncio_zabbix_sender-0.2.1.dist-info/WHEEL
asyncio_zabbix_sender-0.2.1.dist-info/METADATA
asyncio_zabbix_sender-0.2.1.dist-info/LICENSE
asyncio_zabbix_sender-0.2.1.dist-info/RECORD
