Metadata-Version: 2.1
Name: asyncio-zabbix-sender
Version: 0.2.1
Summary: Asyncio implementation of the Zabbix Sender protocol
Home-page: https://github.com/mastdi/asyncio-zabbix-sender
License: Apache-2.0
Author: Martin Storgaard Dieu
Author-email: martin@storgaarddieu.com
Requires-Python: >=3.8,<4.0
Classifier: License :: OSI Approved :: Apache Software License
Classifier: Programming Language :: Python :: 3
Classifier: Programming Language :: Python :: 3.8
Classifier: Programming Language :: Python :: 3.9
Classifier: Programming Language :: Python :: 3.10
Classifier: Programming Language :: Python :: 3.11
Project-URL: Repository, https://github.com/mastdi/asyncio-zabbix-sender
